{
  "politician": "宮本周司",
  "organizations": [
    "宮本しゅうじ後援会",
    "税理士による宮本周司後援会"
  ],
  "generated_at": "2026-04-04T18:05:58.254877",
  "2023": {
    "total_income": 37136490,
    "total_expense": 6912252,
    "income_count": 2,
    "expense_count": 48,
    "income_by_type": {
      "個人の負担する党費又は会費": 18636490,
      "寄附": 18500000
    },
    "expense_by_type": {
      "経常経費": 3276819,
      "組織活動費": 1902401,
      "事務所費": 871389,
      "宣伝事業費": 424123,
      "渉外費": 316860,
      "その他の支出": 120660
    },
    "donor_ranking": [
      {
        "name": "党費又は会費を納入した者の負担",
        "amount": 18636490
      },
      {
        "name": "全国商工政治",
        "amount": 18500000
      }
    ]
  }
}